[
  {
    "id": 1,
    "nameCN": "勇",
    "category": "资质",
    "scale": 10,
    "valueType": "小数",
    "field5": 0,
    "calculationType": "乘法",
    "description": "勇敢的",
    "maxValue": 0,
    "field9": 0,
    "field10": 1,
    "field11": 0,
    "nameEN": "Str"
  },
  {
    "id": 2,
    "nameCN": "智",
    "category": "资质",
    "scale": 10,
    "valueType": "小数",
    "field5": 0,
    "calculationType": "乘法",
    "description": "智慧的",
    "maxValue": 0,
    "field9": 0,
    "field10": 1,
    "field11": 0,
    "nameEN": "Int"
  },
  {
    "id": 3,
    "nameCN": "体",
    "category": "资质",
    "scale": 10,
    "valueType": "小数",
    "field5": 0,
    "calculationType": "乘法",
    "description": "体能的",
    "maxValue": 0,
    "field9": 0,
    "field10": 1,
    "field11": 0,
    "nameEN": "Con"
  },
  {
    "id": 4,
    "nameCN": "敏",
    "category": "资质",
    "scale": 10,
    "valueType": "小数",
    "field5": 0,
    "calculationType": "乘法",
    "description": "敏捷的",
    "maxValue": 0,
    "field9": 0,
    "field10": 1,
    "field11": 0,
    "nameEN": "Agi"
  },
  {
    "id": 5,
    "nameCN": "精",
    "category": "资质",
    "scale": 10,
    "valueType": "小数",
    "field5": 0,
    "calculationType": "乘法",
    "description": "精神的",
    "maxValue": 0,
    "field9": 0,
    "field10": 1,
    "field11": 0,
    "nameEN": "spirit"
  },
  {
    "id": 6,
    "nameCN": "生命",
    "category": "核心",
    "scale": 10000,
    "valueType": "整数",
    "field5": 0,
    "calculationType": "指数",
    "description": "生命的",
    "maxValue": 0,
    "field9": 0,
    "field10": 1,
    "field11": 1,
    "nameEN": "HP"
  },
  {
    "id": 7,
    "nameCN": "速度",
    "category": "核心",
    "scale": 5,
    "valueType": "整数",
    "field5": 10000,
    "calculationType": "乘法",
    "description": "速度的",
    "maxValue": 0,
    "field9": 0,
    "field10": 1,
    "field11": 1,
    "nameEN": "Speed"
  },
  {
    "id": 8,
    "nameCN": "物攻",
    "category": "核心",
    "scale": 2000,
    "valueType": "整数",
    "field5": 0,
    "calculationType": "指数",
    "description": "勇士的",
    "maxValue": 0,
    "field9": 0,
    "field10": 1,
    "field11": 1,
    "nameEN": "ATK"
  },
  {
    "id": 9,
    "nameCN": "物防",
    "category": "核心",
    "scale": 1000,
    "valueType": "整数",
    "field5": 0,
    "calculationType": "指数",
    "description": "厚重的",
    "maxValue": 0,
    "field9": 0,
    "field10": 1,
    "field11": 1,
    "nameEN": "DEF"
  },
  {
    "id": 10,
    "nameCN": "法攻",
    "category": "核心",
    "scale": 2000,
    "valueType": "整数",
    "field5": 0,
    "calculationType": "指数",
    "description": "法师的",
    "maxValue": 0,
    "field9": 0,
    "field10": 1,
    "field11": 1,
    "nameEN": "MATK"
  },
  {
    "id": 11,
    "nameCN": "法防",
    "category": "核心",
    "scale": 1000,
    "valueType": "整数",
    "field5": 0,
    "calculationType": "指数",
    "description": "坚韧的",
    "maxValue": 0,
    "field9": 0,
    "field10": 1,
    "field11": 1,
    "nameEN": "MDEF"
  },
  {
    "id": 12,
    "nameCN": "暴击几率",
    "category": "附加",
    "scale": 6,
    "valueType": "百分比",
    "field5": 500,
    "calculationType": "乘法",
    "description": "暴击的",
    "maxValue": 100,
    "field9": 500,
    "field10": 1,
    "field11": 1,
    "nameEN": "[size=10]crit chance"
  },
  {
    "id": 13,
    "nameCN": "暴击伤害",
    "category": "附加",
    "scale": 40,
    "valueType": "百分比",
    "field5": 15000,
    "calculationType": "乘法",
    "description": "暴伤的",
    "maxValue": 0,
    "field9": 5000,
    "field10": 1,
    "field11": 1,
    "nameEN": "[size=10]crit damage"
  },
  {
    "id": 14,
    "nameCN": "吸血比例",
    "category": "附加",
    "scale": 3,
    "valueType": "百分比",
    "field5": 0,
    "calculationType": "乘法",
    "description": "吸血的",
    "maxValue": 0,
    "field9": 300,
    "field10": 1,
    "field11": 1,
    "nameEN": "[size=10]life steal"
  },
  {
    "id": 15,
    "nameCN": "生命恢复",
    "category": "附加",
    "scale": 200,
    "valueType": "每秒",
    "field5": 0,
    "calculationType": "指数",
    "description": "自愈的",
    "maxValue": 0,
    "field9": 0,
    "field10": 1,
    "field11": 1,
    "nameEN": "[size=10]health regen"
  },
  {
    "id": 16,
    "nameCN": "治疗加成",
    "category": "附加",
    "scale": 20,
    "valueType": "百分比",
    "field5": 0,
    "calculationType": "乘法",
    "description": "治疗的",
    "maxValue": 0,
    "field9": 1500,
    "field10": 1,
    "field11": 1,
    "nameEN": "[size=10]heal bonus"
  },
  {
    "id": 17,
    "nameCN": "护盾加成",
    "category": "附加",
    "scale": 20,
    "valueType": "百分比",
    "field5": 0,
    "calculationType": "乘法",
    "description": "护盾的",
    "maxValue": 0,
    "field9": 1500,
    "field10": 1,
    "field11": 0,
    "nameEN": "[size=10]shield bonus"
  },
  {
    "id": 18,
    "nameCN": "命中修正",
    "category": "附加",
    "scale": 5,
    "valueType": "百分比",
    "field5": 0,
    "calculationType": "乘法",
    "description": "命中的",
    "maxValue": 0,
    "field9": 1000,
    "field10": 1,
    "field11": 1,
    "nameEN": "[size=10]Hit rate"
  },
  {
    "id": 19,
    "nameCN": "闪避修正",
    "category": "附加",
    "scale": 5,
    "valueType": "百分比",
    "field5": 0,
    "calculationType": "乘法",
    "description": "闪避的",
    "maxValue": 0,
    "field9": 1000,
    "field10": 1,
    "field11": 1,
    "nameEN": "[size=10]Evasion rate"
  },
  {
    "id": 20,
    "nameCN": "物理增伤",
    "category": "附加",
    "scale": 20,
    "valueType": "百分比",
    "field5": 0,
    "calculationType": "乘法",
    "description": "战士的",
    "maxValue": 0,
    "field9": 1500,
    "field10": 1,
    "field11": 1,
    "nameEN": "[size=10]phys damage"
  },
  {
    "id": 21,
    "nameCN": "物理减伤",
    "category": "附加",
    "scale": 8,
    "valueType": "百分比",
    "field5": 0,
    "calculationType": "乘法",
    "description": "龟甲的",
    "maxValue": 80,
    "field9": 750,
    "field10": 1,
    "field11": 1,
    "nameEN": "[size=10]phys damage red"
  },
  {
    "id": 22,
    "nameCN": "法术增伤",
    "category": "附加",
    "scale": 20,
    "valueType": "百分比",
    "field5": 0,
    "calculationType": "乘法",
    "description": "异能的",
    "maxValue": 0,
    "field9": 1500,
    "field10": 1,
    "field11": 1,
    "nameEN": "[size=10]spell damage"
  },
  {
    "id": 23,
    "nameCN": "法术减伤",
    "category": "附加",
    "scale": 8,
    "valueType": "百分比",
    "field5": 0,
    "calculationType": "乘法",
    "description": "结界的",
    "maxValue": 80,
    "field9": 750,
    "field10": 1,
    "field11": 1,
    "nameEN": "[size=10]spell damage red"
  },
  {
    "id": 24,
    "nameCN": "护盾超限",
    "category": "附加",
    "scale": 20,
    "valueType": "百分比",
    "field5": 0,
    "calculationType": "乘法",
    "description": "超盾的",
    "maxValue": 0,
    "field9": 1500,
    "field10": 1,
    "field11": 0,
    "nameEN": "Shield limit"
  },
  {
    "id": 25,
    "nameCN": "普攻增伤",
    "category": "附加",
    "scale": 20,
    "valueType": "百分比",
    "field5": 0,
    "calculationType": "乘法",
    "description": "鹰击的",
    "maxValue": 0,
    "field9": 2000,
    "field10": 1,
    "field11": 1,
    "nameEN": "[size=10]normal attack damage"
  },
  {
    "id": 26,
    "nameCN": "最终增伤",
    "category": "附加",
    "scale": 10,
    "valueType": "百分比",
    "field5": 0,
    "calculationType": "乘法",
    "description": "凤羽的",
    "maxValue": 0,
    "field9": 1000,
    "field10": 1,
    "field11": 1,
    "nameEN": "[size=10]final damage"
  },
  {
    "id": 27,
    "nameCN": "最终减伤",
    "category": "附加",
    "scale": 4,
    "valueType": "百分比",
    "field5": 0,
    "calculationType": "乘法",
    "description": "龙鳞的",
    "maxValue": 80,
    "field9": 750,
    "field10": 1,
    "field11": 1,
    "nameEN": "[size=10]final damage red"
  },
  {
    "id": 28,
    "nameCN": "初始能量",
    "category": "特殊",
    "scale": 100,
    "valueType": "整数",
    "field5": 0,
    "calculationType": "固定",
    "description": "聚能的",
    "maxValue": 5,
    "field9": 100,
    "field10": 1,
    "field11": 1,
    "nameEN": "Init Energy"
  },
  {
    "id": 29,
    "nameCN": "能量回复",
    "category": "特殊",
    "scale": 100,
    "valueType": "整数",
    "field5": 100,
    "calculationType": "固定",
    "description": "凝神的",
    "maxValue": 5,
    "field9": 100,
    "field10": 1,
    "field11": 1,
    "nameEN": "[size=10]energy regen"
  },
  {
    "id": 30,
    "nameCN": "武器熟练",
    "category": "特殊",
    "scale": 20,
    "valueType": "百分比",
    "field5": 0,
    "calculationType": "乘法",
    "description": "熟练的",
    "maxValue": 0,
    "field9": 1500,
    "field10": 1,
    "field11": 0,
    "nameEN": "Weapon Proficiency"
  },
  {
    "id": 31,
    "nameCN": "召唤强度",
    "category": "特殊",
    "scale": 20,
    "valueType": "百分比",
    "field5": 0,
    "calculationType": "乘法",
    "description": "召唤的",
    "maxValue": 0,
    "field9": 1200,
    "field10": 1,
    "field11": 0,
    "nameEN": "[size=10]summoning strength"
  },
  {
    "id": 32,
    "nameCN": "召唤数量",
    "category": "特殊",
    "scale": 100,
    "valueType": "整数",
    "field5": 0,
    "calculationType": "固定",
    "description": "通灵的",
    "maxValue": 3,
    "field9": 100,
    "field10": 1,
    "field11": 0,
    "nameEN": "[size=10]summoning quantity"
  },
  {
    "id": 33,
    "nameCN": "召唤时间",
    "category": "特殊",
    "scale": 50,
    "valueType": "百分比",
    "field5": 0,
    "calculationType": "乘法",
    "description": "空间的",
    "maxValue": 0,
    "field9": 2000,
    "field10": 1,
    "field11": 0,
    "nameEN": "[size=10]summoning time"
  },
  {
    "id": 34,
    "nameCN": "增益时间",
    "category": "特殊",
    "scale": 50,
    "valueType": "百分比",
    "field5": 0,
    "calculationType": "乘法",
    "description": "祝福的",
    "maxValue": 0,
    "field9": 2000,
    "field10": 1,
    "field11": 0,
    "nameEN": "[size=10]buff duration"
  },
  {
    "id": 35,
    "nameCN": "减益时间",
    "category": "特殊",
    "scale": 50,
    "valueType": "百分比",
    "field5": 0,
    "calculationType": "乘法",
    "description": "诅咒的",
    "maxValue": 0,
    "field9": 2000,
    "field10": 1,
    "field11": 0,
    "nameEN": "[size=10]debuff duration"
  },
  {
    "id": 36,
    "nameCN": "灵兽经验",
    "category": "特殊",
    "scale": 20,
    "valueType": "百分比",
    "field5": 0,
    "calculationType": "乘法",
    "description": "御兽的",
    "maxValue": 0,
    "field9": 1500,
    "field10": 1,
    "field11": 0,
    "nameEN": "[size=10]pet Exp"
  },
  {
    "id": 37,
    "nameCN": "技能冷却",
    "category": "特殊",
    "scale": 10,
    "valueType": "百分比",
    "field5": 0,
    "calculationType": "乘法",
    "description": "时间的",
    "maxValue": 95,
    "field9": 1500,
    "field10": 1,
    "field11": 1,
    "nameEN": "[size=10]skill cooldown"
  },
  {
    "id": 38,
    "nameCN": "受疗效果",
    "category": "特殊",
    "scale": 20,
    "valueType": "百分比",
    "field5": 0,
    "calculationType": "乘法",
    "description": "受疗的",
    "maxValue": 0,
    "field9": 2000,
    "field10": 1,
    "field11": 1,
    "nameEN": "[size=10]Heal Received"
  },
  {
    "id": 39,
    "nameCN": "技能学习",
    "category": "特殊",
    "scale": 20,
    "valueType": "百分比",
    "field5": 0,
    "calculationType": "乘法",
    "description": "修炼的",
    "maxValue": 0,
    "field9": 1500,
    "field10": 1,
    "field11": 0,
    "nameEN": "[size=10]skill learning"
  },
  {
    "id": 40,
    "nameCN": "经验加成",
    "category": "特殊",
    "scale": 20,
    "valueType": "百分比",
    "field5": 0,
    "calculationType": "乘法",
    "description": "经验的",
    "maxValue": 0,
    "field9": 1500,
    "field10": 1,
    "field11": 0,
    "nameEN": "[size=10]exp bonus"
  },
  {
    "id": 41,
    "nameCN": "职业成长",
    "category": "特殊",
    "scale": 20,
    "valueType": "百分比",
    "field5": 0,
    "calculationType": "乘法",
    "description": "职业的",
    "maxValue": 0,
    "field9": 1500,
    "field10": 1,
    "field11": 0,
    "nameEN": "[size=10]career growth"
  },
  {
    "id": 42,
    "nameCN": "物品掉落",
    "category": "特殊",
    "scale": 5,
    "valueType": "百分比",
    "field5": 0,
    "calculationType": "乘法",
    "description": "幸运的",
    "maxValue": 0,
    "field9": 1000,
    "field10": 1,
    "field11": 0,
    "nameEN": "[size=10]item drop"
  },
  {
    "id": 43,
    "nameCN": "工作效率",
    "category": "特殊",
    "scale": 20,
    "valueType": "百分比",
    "field5": 0,
    "calculationType": "乘法",
    "description": "工匠的",
    "maxValue": 0,
    "field9": 2000,
    "field10": 1,
    "field11": 0,
    "nameEN": "[size=10]work efficiency"
  },
  {
    "id": 44,
    "nameCN": "雷系增伤",
    "category": "元素",
    "scale": 20,
    "valueType": "百分比",
    "field5": 0,
    "calculationType": "乘法",
    "description": "天空的",
    "maxValue": 0,
    "field9": 1500,
    "field10": 1,
    "field11": 1,
    "nameEN": "[size=10]Lightning Dmg"
  },
  {
    "id": 45,
    "nameCN": "雷系抗性",
    "category": "元素",
    "scale": 8,
    "valueType": "百分比",
    "field5": 0,
    "calculationType": "乘法",
    "description": "雷鸣的",
    "maxValue": 80,
    "field9": 750,
    "field10": 1,
    "field11": 1,
    "nameEN": "[size=10]Lightning Def"
  },
  {
    "id": 46,
    "nameCN": "水系增伤",
    "category": "元素",
    "scale": 20,
    "valueType": "百分比",
    "field5": 0,
    "calculationType": "乘法",
    "description": "海洋的",
    "maxValue": 0,
    "field9": 1500,
    "field10": 1,
    "field11": 1,
    "nameEN": "[size=10]Water Dmg"
  },
  {
    "id": 47,
    "nameCN": "水系抗性",
    "category": "元素",
    "scale": 8,
    "valueType": "百分比",
    "field5": 0,
    "calculationType": "乘法",
    "description": "潮汐的",
    "maxValue": 80,
    "field9": 750,
    "field10": 1,
    "field11": 1,
    "nameEN": "[size=10]Water Def"
  },
  {
    "id": 48,
    "nameCN": "火系增伤",
    "category": "元素",
    "scale": 20,
    "valueType": "百分比",
    "field5": 0,
    "calculationType": "乘法",
    "description": "火山的",
    "maxValue": 0,
    "field9": 1500,
    "field10": 1,
    "field11": 1,
    "nameEN": "[size=10]Fire Dmg"
  },
  {
    "id": 49,
    "nameCN": "火系抗性",
    "category": "元素",
    "scale": 8,
    "valueType": "百分比",
    "field5": 0,
    "calculationType": "乘法",
    "description": "熔岩的",
    "maxValue": 80,
    "field9": 750,
    "field10": 1,
    "field11": 1,
    "nameEN": "[size=10]Fire Def"
  },
  {
    "id": 50,
    "nameCN": "木系增伤",
    "category": "元素",
    "scale": 20,
    "valueType": "百分比",
    "field5": 0,
    "calculationType": "乘法",
    "description": "森林的",
    "maxValue": 0,
    "field9": 1500,
    "field10": 1,
    "field11": 1,
    "nameEN": "[size=10]Wood Dmg"
  },
  {
    "id": 51,
    "nameCN": "木系抗性",
    "category": "元素",
    "scale": 8,
    "valueType": "百分比",
    "field5": 0,
    "calculationType": "乘法",
    "description": "树精的",
    "maxValue": 80,
    "field9": 750,
    "field10": 1,
    "field11": 1,
    "nameEN": "[size=10]Wood Def"
  },
  {
    "id": 52,
    "nameCN": "土系增伤",
    "category": "元素",
    "scale": 20,
    "valueType": "百分比",
    "field5": 0,
    "calculationType": "乘法",
    "description": "大地的",
    "maxValue": 0,
    "field9": 1500,
    "field10": 1,
    "field11": 1,
    "nameEN": "[size=10]Earth Dmg"
  },
  {
    "id": 53,
    "nameCN": "土系抗性",
    "category": "元素",
    "scale": 8,
    "valueType": "百分比",
    "field5": 0,
    "calculationType": "乘法",
    "description": "岩石的",
    "maxValue": 80,
    "field9": 750,
    "field10": 1,
    "field11": 1,
    "nameEN": "[size=10]Earth Def"
  },
  {
    "id": 54,
    "nameCN": "精神增伤",
    "category": "元素",
    "scale": 20,
    "valueType": "百分比",
    "field5": 0,
    "calculationType": "乘法",
    "description": "幻想的",
    "maxValue": 0,
    "field9": 1500,
    "field10": 1,
    "field11": 1,
    "nameEN": "[size=10]spirit Dmg"
  },
  {
    "id": 55,
    "nameCN": "精神抗性",
    "category": "元素",
    "scale": 8,
    "valueType": "百分比",
    "field5": 0,
    "calculationType": "乘法",
    "description": "意志的",
    "maxValue": 80,
    "field9": 750,
    "field10": 1,
    "field11": 1,
    "nameEN": "[size=10]spirit Def"
  },
  {
    "id": 56,
    "nameCN": "神圣增伤",
    "category": "元素",
    "scale": 20,
    "valueType": "百分比",
    "field5": 0,
    "calculationType": "乘法",
    "description": "神圣的",
    "maxValue": 0,
    "field9": 1500,
    "field10": 1,
    "field11": 1,
    "nameEN": "[size=10]holy Dmg"
  },
  {
    "id": 57,
    "nameCN": "神圣抗性",
    "category": "元素",
    "scale": 8,
    "valueType": "百分比",
    "field5": 0,
    "calculationType": "乘法",
    "description": "圣洁的",
    "maxValue": 80,
    "field9": 750,
    "field10": 1,
    "field11": 1,
    "nameEN": "[size=10]holy Def"
  },
  {
    "id": 58,
    "nameCN": "黑暗增伤",
    "category": "元素",
    "scale": 20,
    "valueType": "百分比",
    "field5": 0,
    "calculationType": "乘法",
    "description": "黑暗的",
    "maxValue": 0,
    "field9": 1500,
    "field10": 1,
    "field11": 1,
    "nameEN": "[size=10]Dark Dmg"
  },
  {
    "id": 59,
    "nameCN": "黑暗抗性",
    "category": "元素",
    "scale": 8,
    "valueType": "百分比",
    "field5": 0,
    "calculationType": "乘法",
    "description": "邪恶的",
    "maxValue": 80,
    "field9": 750,
    "field10": 1,
    "field11": 1,
    "nameEN": "[size=10]Dark Def"
  },
  {
    "id": 60,
    "nameCN": "通用类效果",
    "category": "技能效果",
    "scale": 25,
    "valueType": "百分比",
    "field5": 0,
    "calculationType": "乘法",
    "description": "通用的",
    "maxValue": 0,
    "field9": 1500,
    "field10": 1,
    "field11": 1,
    "nameEN": "[size=10]Genera effect"
  },
  {
    "id": 61,
    "nameCN": "战技类效果",
    "category": "技能效果",
    "scale": 25,
    "valueType": "百分比",
    "field5": 0,
    "calculationType": "乘法",
    "description": "战技的",
    "maxValue": 0,
    "field9": 1500,
    "field10": 1,
    "field11": 1,
    "nameEN": "[size=10]Combat effect"
  },
  {
    "id": 62,
    "nameCN": "武功类效果",
    "category": "技能效果",
    "scale": 25,
    "valueType": "百分比",
    "field5": 0,
    "calculationType": "乘法",
    "description": "武功的",
    "maxValue": 0,
    "field9": 1500,
    "field10": 1,
    "field11": 1,
    "nameEN": "[size=10]Kung fu effect"
  },
  {
    "id": 63,
    "nameCN": "符咒类效果",
    "category": "技能效果",
    "scale": 25,
    "valueType": "百分比",
    "field5": 0,
    "calculationType": "乘法",
    "description": "符咒的",
    "maxValue": 0,
    "field9": 1500,
    "field10": 1,
    "field11": 1,
    "nameEN": "[size=10]Spell effect"
  },
  {
    "id": 64,
    "nameCN": "箭弩类效果",
    "category": "技能效果",
    "scale": 25,
    "valueType": "百分比",
    "field5": 0,
    "calculationType": "乘法",
    "description": "箭弩的",
    "maxValue": 0,
    "field9": 1500,
    "field10": 1,
    "field11": 1,
    "nameEN": "[size=10]Archery effect"
  },
  {
    "id": 65,
    "nameCN": "方术类效果",
    "category": "技能效果",
    "scale": 25,
    "valueType": "百分比",
    "field5": 0,
    "calculationType": "乘法",
    "description": "方术的",
    "maxValue": 0,
    "field9": 1500,
    "field10": 1,
    "field11": 1,
    "nameEN": "[size=10]Sorcery effect"
  },
  {
    "id": 66,
    "nameCN": "异能类效果",
    "category": "技能效果",
    "scale": 25,
    "valueType": "百分比",
    "field5": 0,
    "calculationType": "乘法",
    "description": "异能的",
    "maxValue": 0,
    "field9": 1500,
    "field10": 1,
    "field11": 1,
    "nameEN": "[size=10]Superpower effect"
  },
  {
    "id": 67,
    "nameCN": "神技类效果",
    "category": "技能效果",
    "scale": 25,
    "valueType": "百分比",
    "field5": 0,
    "calculationType": "乘法",
    "description": "神技的",
    "maxValue": 0,
    "field9": 1500,
    "field10": 1,
    "field11": 1,
    "nameEN": "[size=10]Sorcery effect"
  },
  {
    "id": 68,
    "nameCN": "斗气类效果",
    "category": "技能效果",
    "scale": 25,
    "valueType": "百分比",
    "field5": 0,
    "calculationType": "乘法",
    "description": "斗气的",
    "maxValue": 0,
    "field9": 1500,
    "field10": 1,
    "field11": 1,
    "nameEN": "[size=10]Boxing effect"
  },
  {
    "id": 69,
    "nameCN": "忍术类效果",
    "category": "技能效果",
    "scale": 25,
    "valueType": "百分比",
    "field5": 0,
    "calculationType": "乘法",
    "description": "忍术的",
    "maxValue": 0,
    "field9": 1500,
    "field10": 1,
    "field11": 1,
    "nameEN": "[size=10]Ninjutsu effect"
  },
  {
    "id": 70,
    "nameCN": "魔法类效果",
    "category": "技能效果",
    "scale": 25,
    "valueType": "百分比",
    "field5": 0,
    "calculationType": "乘法",
    "description": "魔法的",
    "maxValue": 0,
    "field9": 1500,
    "field10": 1,
    "field11": 1,
    "nameEN": "[size=10]Magic effect"
  },
  {
    "id": 71,
    "nameCN": "功法类效果",
    "category": "技能效果",
    "scale": 25,
    "valueType": "百分比",
    "field5": 0,
    "calculationType": "乘法",
    "description": "功法的",
    "maxValue": 0,
    "field9": 1500,
    "field10": 1,
    "field11": 1,
    "nameEN": "[size=10]Xiuzhen effect"
  },
  {
    "id": 72,
    "nameCN": "枪械类效果",
    "category": "技能效果",
    "scale": 25,
    "valueType": "百分比",
    "field5": 0,
    "calculationType": "乘法",
    "description": "枪械的",
    "maxValue": 0,
    "field9": 1500,
    "field10": 1,
    "field11": 1,
    "nameEN": "[size=10]Marksmanship effect"
  },
  {
    "id": 73,
    "nameCN": "机甲类效果",
    "category": "技能效果",
    "scale": 25,
    "valueType": "百分比",
    "field5": 0,
    "calculationType": "乘法",
    "description": "机甲的",
    "maxValue": 0,
    "field9": 1500,
    "field10": 1,
    "field11": 1,
    "nameEN": "[size=10]Mecha effect"
  },
  {
    "id": 74,
    "nameCN": "召唤类效果",
    "category": "技能效果",
    "scale": 25,
    "valueType": "百分比",
    "field5": 0,
    "calculationType": "乘法",
    "description": "召唤的",
    "maxValue": 0,
    "field9": 1500,
    "field10": 1,
    "field11": 1,
    "nameEN": "[size=10]Summons effect"
  },
  {
    "id": 75,
    "nameCN": "医术类效果",
    "category": "技能效果",
    "scale": 25,
    "valueType": "百分比",
    "field5": 0,
    "calculationType": "乘法",
    "description": "医术的",
    "maxValue": 0,
    "field9": 1500,
    "field10": 1,
    "field11": 1,
    "nameEN": "[size=10]Medicine effect"
  },
  {
    "id": 76,
    "nameCN": "通用类等级",
    "category": "技能等级",
    "scale": 10,
    "valueType": "整数",
    "field5": 0,
    "calculationType": "乘法",
    "description": "通用的",
    "maxValue": 0,
    "field9": 100,
    "field10": 1,
    "field11": 0,
    "nameEN": "[size=10]General Level"
  },
  {
    "id": 77,
    "nameCN": "战技类等级",
    "category": "技能等级",
    "scale": 10,
    "valueType": "整数",
    "field5": 0,
    "calculationType": "乘法",
    "description": "战技的",
    "maxValue": 0,
    "field9": 100,
    "field10": 1,
    "field11": 0,
    "nameEN": "[size=10]Combatl Level"
  },
  {
    "id": 78,
    "nameCN": "武功类等级",
    "category": "技能等级",
    "scale": 10,
    "valueType": "整数",
    "field5": 0,
    "calculationType": "乘法",
    "description": "武功的",
    "maxValue": 0,
    "field9": 100,
    "field10": 1,
    "field11": 0,
    "nameEN": "[size=10]Kung ful Level"
  },
  {
    "id": 79,
    "nameCN": "符咒类等级",
    "category": "技能等级",
    "scale": 10,
    "valueType": "整数",
    "field5": 0,
    "calculationType": "乘法",
    "description": "符咒的",
    "maxValue": 0,
    "field9": 100,
    "field10": 1,
    "field11": 0,
    "nameEN": "[size=10]Spelll Level"
  },
  {
    "id": 80,
    "nameCN": "箭弩类等级",
    "category": "技能等级",
    "scale": 10,
    "valueType": "整数",
    "field5": 0,
    "calculationType": "乘法",
    "description": "箭弩的",
    "maxValue": 0,
    "field9": 100,
    "field10": 1,
    "field11": 0,
    "nameEN": "[size=10]Archeryl Level"
  },
  {
    "id": 81,
    "nameCN": "方术类等级",
    "category": "技能等级",
    "scale": 10,
    "valueType": "整数",
    "field5": 0,
    "calculationType": "乘法",
    "description": "方术的",
    "maxValue": 0,
    "field9": 100,
    "field10": 1,
    "field11": 0,
    "nameEN": "[size=10]Sorceryl Level"
  },
  {
    "id": 82,
    "nameCN": "异能类等级",
    "category": "技能等级",
    "scale": 10,
    "valueType": "整数",
    "field5": 0,
    "calculationType": "乘法",
    "description": "异能的",
    "maxValue": 0,
    "field9": 100,
    "field10": 1,
    "field11": 0,
    "nameEN": "[size=10]Superpowerl Level"
  },
  {
    "id": 83,
    "nameCN": "神技类等级",
    "category": "技能等级",
    "scale": 10,
    "valueType": "整数",
    "field5": 0,
    "calculationType": "乘法",
    "description": "神技的",
    "maxValue": 0,
    "field9": 100,
    "field10": 1,
    "field11": 0,
    "nameEN": "[size=10]Sorceryl Level"
  },
  {
    "id": 84,
    "nameCN": "斗气类等级",
    "category": "技能等级",
    "scale": 10,
    "valueType": "整数",
    "field5": 0,
    "calculationType": "乘法",
    "description": "斗气的",
    "maxValue": 0,
    "field9": 100,
    "field10": 1,
    "field11": 0,
    "nameEN": "[size=10]Boxingl Level"
  },
  {
    "id": 85,
    "nameCN": "忍术类等级",
    "category": "技能等级",
    "scale": 10,
    "valueType": "整数",
    "field5": 0,
    "calculationType": "乘法",
    "description": "忍术的",
    "maxValue": 0,
    "field9": 100,
    "field10": 1,
    "field11": 0,
    "nameEN": "[size=10]Ninjutsul Level"
  },
  {
    "id": 86,
    "nameCN": "魔法类等级",
    "category": "技能等级",
    "scale": 10,
    "valueType": "整数",
    "field5": 0,
    "calculationType": "乘法",
    "description": "魔法的",
    "maxValue": 0,
    "field9": 100,
    "field10": 1,
    "field11": 0,
    "nameEN": "[size=10]Magicl Level"
  },
  {
    "id": 87,
    "nameCN": "功法类等级",
    "category": "技能等级",
    "scale": 10,
    "valueType": "整数",
    "field5": 0,
    "calculationType": "乘法",
    "description": "功法的",
    "maxValue": 0,
    "field9": 100,
    "field10": 1,
    "field11": 0,
    "nameEN": "[size=10]Xiuzhenl Level"
  },
  {
    "id": 88,
    "nameCN": "枪械类等级",
    "category": "技能等级",
    "scale": 10,
    "valueType": "整数",
    "field5": 0,
    "calculationType": "乘法",
    "description": "枪械的",
    "maxValue": 0,
    "field9": 100,
    "field10": 1,
    "field11": 0,
    "nameEN": "[size=10]Marksmanshipl Level"
  },
  {
    "id": 89,
    "nameCN": "机甲类等级",
    "category": "技能等级",
    "scale": 10,
    "valueType": "整数",
    "field5": 0,
    "calculationType": "乘法",
    "description": "机甲的",
    "maxValue": 0,
    "field9": 100,
    "field10": 1,
    "field11": 0,
    "nameEN": "[size=10]Mechal Level"
  },
  {
    "id": 90,
    "nameCN": "召唤类等级",
    "category": "技能等级",
    "scale": 10,
    "valueType": "整数",
    "field5": 0,
    "calculationType": "乘法",
    "description": "召唤的",
    "maxValue": 0,
    "field9": 100,
    "field10": 1,
    "field11": 0,
    "nameEN": "[size=10]Summonsl Level"
  },
  {
    "id": 91,
    "nameCN": "医术类等级",
    "category": "技能等级",
    "scale": 10,
    "valueType": "整数",
    "field5": 0,
    "calculationType": "乘法",
    "description": "医术的",
    "maxValue": 0,
    "field9": 100,
    "field10": 1,
    "field11": 0,
    "nameEN": "[size=10]Medicinel Level"
  },
  {
    "id": 92,
    "nameCN": "长柄增伤",
    "category": "熟练伤害",
    "scale": 25,
    "valueType": "百分比",
    "field5": 0,
    "calculationType": "乘法",
    "description": "长柄的",
    "maxValue": 0,
    "field9": 1500,
    "field10": 1,
    "field11": 0,
    "nameEN": "[size=10]polearm damage"
  },
  {
    "id": 93,
    "nameCN": "刀剑增伤",
    "category": "熟练伤害",
    "scale": 25,
    "valueType": "百分比",
    "field5": 0,
    "calculationType": "乘法",
    "description": "刀剑的",
    "maxValue": 0,
    "field9": 1500,
    "field10": 1,
    "field11": 0,
    "nameEN": "[size=10]sword damage"
  },
  {
    "id": 94,
    "nameCN": "拳指增伤",
    "category": "熟练伤害",
    "scale": 25,
    "valueType": "百分比",
    "field5": 0,
    "calculationType": "乘法",
    "description": "拳指的",
    "maxValue": 0,
    "field9": 1500,
    "field10": 1,
    "field11": 0,
    "nameEN": "[size=10]fist damage"
  },
  {
    "id": 95,
    "nameCN": "暗器增伤",
    "category": "熟练伤害",
    "scale": 25,
    "valueType": "百分比",
    "field5": 0,
    "calculationType": "乘法",
    "description": "暗器的",
    "maxValue": 0,
    "field9": 1500,
    "field10": 1,
    "field11": 0,
    "nameEN": "[size=10]hidden weapon damage"
  },
  {
    "id": 96,
    "nameCN": "法杖增伤",
    "category": "熟练伤害",
    "scale": 25,
    "valueType": "百分比",
    "field5": 0,
    "calculationType": "乘法",
    "description": "法杖的",
    "maxValue": 0,
    "field9": 1500,
    "field10": 1,
    "field11": 0,
    "nameEN": "[size=10]staff damage"
  },
  {
    "id": 97,
    "nameCN": "法球增伤",
    "category": "熟练伤害",
    "scale": 25,
    "valueType": "百分比",
    "field5": 0,
    "calculationType": "乘法",
    "description": "法球的",
    "maxValue": 0,
    "field9": 1500,
    "field10": 1,
    "field11": 0,
    "nameEN": "[size=10]orb damage"
  },
  {
    "id": 98,
    "nameCN": "枪弩增伤",
    "category": "熟练伤害",
    "scale": 25,
    "valueType": "百分比",
    "field5": 0,
    "calculationType": "乘法",
    "description": "枪弩的",
    "maxValue": 0,
    "field9": 1500,
    "field10": 1,
    "field11": 0,
    "nameEN": "[size=10]gun&crossbow damage"
  },
  {
    "id": 99,
    "nameCN": "大炮增伤",
    "category": "熟练伤害",
    "scale": 25,
    "valueType": "百分比",
    "field5": 0,
    "calculationType": "乘法",
    "description": "大炮的",
    "maxValue": 0,
    "field9": 1500,
    "field10": 1,
    "field11": 0,
    "nameEN": "[size=10]cannon damage"
  },
  {
    "id": 100,
    "nameCN": "书卷增伤",
    "category": "熟练伤害",
    "scale": 25,
    "valueType": "百分比",
    "field5": 0,
    "calculationType": "乘法",
    "description": "书卷的",
    "maxValue": 0,
    "field9": 1500,
    "field10": 1,
    "field11": 0,
    "nameEN": "scroll damage"
  },
  {
    "id": 101,
    "nameCN": "仪器增伤",
    "category": "熟练伤害",
    "scale": 25,
    "valueType": "百分比",
    "field5": 0,
    "calculationType": "乘法",
    "description": "仪器的",
    "maxValue": 0,
    "field9": 1500,
    "field10": 1,
    "field11": 0,
    "nameEN": "[size=10]instrument damage"
  },
  {
    "id": 102,
    "nameCN": "驯兽等级",
    "category": "能力",
    "scale": 100,
    "valueType": "整数",
    "field5": 0,
    "calculationType": "固定",
    "description": "驯兽的",
    "maxValue": 5,
    "field9": 100,
    "field10": 0,
    "field11": 0,
    "nameEN": "[size=10]Animals Level"
  },
  {
    "id": 103,
    "nameCN": "管理等级",
    "category": "能力",
    "scale": 100,
    "valueType": "整数",
    "field5": 0,
    "calculationType": "固定",
    "description": "管理的",
    "maxValue": 5,
    "field9": 100,
    "field10": 0,
    "field11": 0,
    "nameEN": "[size=12]Manage Level"
  },
  {
    "id": 104,
    "nameCN": "锻造等级",
    "category": "能力",
    "scale": 100,
    "valueType": "整数",
    "field5": 0,
    "calculationType": "固定",
    "description": "锻造的",
    "maxValue": 5,
    "field9": 100,
    "field10": 0,
    "field11": 0,
    "nameEN": "[size=10]Forge Level"
  },
  {
    "id": 105,
    "nameCN": "修习等级",
    "category": "能力",
    "scale": 100,
    "valueType": "整数",
    "field5": 0,
    "calculationType": "固定",
    "description": "修习的",
    "maxValue": 5,
    "field9": 100,
    "field10": 0,
    "field11": 0,
    "nameEN": "[size=10]Study Level"
  },
  {
    "id": 106,
    "nameCN": "研究等级",
    "category": "能力",
    "scale": 100,
    "valueType": "整数",
    "field5": 0,
    "calculationType": "固定",
    "description": "研究的",
    "maxValue": 5,
    "field9": 100,
    "field10": 0,
    "field11": 0,
    "nameEN": "[size=10]Research Level"
  },
  {
    "id": 107,
    "nameCN": "建造等级",
    "category": "能力",
    "scale": 100,
    "valueType": "整数",
    "field5": 0,
    "calculationType": "固定",
    "description": "建造的",
    "maxValue": 5,
    "field9": 100,
    "field10": 0,
    "field11": 0,
    "nameEN": "[size=10]Build Level"
  },
  {
    "id": 108,
    "nameCN": "商业等级",
    "category": "能力",
    "scale": 100,
    "valueType": "整数",
    "field5": 0,
    "calculationType": "固定",
    "description": "商业的",
    "maxValue": 5,
    "field9": 100,
    "field10": 0,
    "field11": 0,
    "nameEN": "[size=10]Commerce Level"
  },
  {
    "id": 109,
    "nameCN": "合成等级",
    "category": "能力",
    "scale": 100,
    "valueType": "整数",
    "field5": 0,
    "calculationType": "固定",
    "description": "合成的",
    "maxValue": 5,
    "field9": 100,
    "field10": 0,
    "field11": 0,
    "nameEN": "[size=10]Pharmacy Level"
  },
  {
    "id": 110,
    "nameCN": "计略等级",
    "category": "能力",
    "scale": 100,
    "valueType": "整数",
    "field5": 0,
    "calculationType": "固定",
    "description": "计略的",
    "maxValue": 5,
    "field9": 100,
    "field10": 0,
    "field11": 0,
    "nameEN": "[size=10]Strategy Level"
  },
  {
    "id": 111,
    "nameCN": "收藏等级",
    "category": "能力",
    "scale": 100,
    "valueType": "整数",
    "field5": 0,
    "calculationType": "固定",
    "description": "收藏的",
    "maxValue": 5,
    "field9": 100,
    "field10": 0,
    "field11": 0,
    "nameEN": "[size=10]History Level"
  },
  {
    "id": 112,
    "nameCN": "生命上限修正",
    "category": "战斗隐藏",
    "scale": 25,
    "valueType": "百分比",
    "field5": 0,
    "calculationType": "乘法",
    "description": "",
    "maxValue": 0,
    "field9": 0,
    "field10": 1,
    "field11": 1
  },
  {
    "id": 113,
    "nameCN": "速度修正",
    "category": "战斗隐藏",
    "scale": 25,
    "valueType": "百分比",
    "field5": 0,
    "calculationType": "乘法",
    "description": "",
    "maxValue": 0,
    "field9": 0,
    "field10": 1,
    "field11": 1,
    "nameEN": "Spd Mod"
  },
  {
    "id": 114,
    "nameCN": "物攻修正",
    "category": "战斗隐藏",
    "scale": 25,
    "valueType": "百分比",
    "field5": 0,
    "calculationType": "乘法",
    "description": "",
    "maxValue": 0,
    "field9": 0,
    "field10": 1,
    "field11": 1,
    "nameEN": "Atk Mod"
  },
  {
    "id": 115,
    "nameCN": "法攻修正",
    "category": "战斗隐藏",
    "scale": 25,
    "valueType": "百分比",
    "field5": 0,
    "calculationType": "乘法",
    "description": "",
    "maxValue": 0,
    "field9": 0,
    "field10": 1,
    "field11": 1,
    "nameEN": "Mag Atk Mod"
  },
  {
    "id": 116,
    "nameCN": "物防修正",
    "category": "战斗隐藏",
    "scale": 25,
    "valueType": "百分比",
    "field5": 0,
    "calculationType": "乘法",
    "description": "",
    "maxValue": 0,
    "field9": 0,
    "field10": 1,
    "field11": 1,
    "nameEN": "Def Mod"
  },
  {
    "id": 117,
    "nameCN": "法防修正",
    "category": "战斗隐藏",
    "scale": 25,
    "valueType": "百分比",
    "field5": 0,
    "calculationType": "乘法",
    "description": "",
    "maxValue": 0,
    "field9": 0,
    "field10": 1,
    "field11": 1,
    "nameEN": "Mag Def Mod"
  },
  {
    "id": 118,
    "nameCN": "受物理伤害",
    "category": "战斗隐藏",
    "scale": 25,
    "valueType": "百分比",
    "field5": 0,
    "calculationType": "乘法",
    "description": "",
    "maxValue": 95,
    "field9": 0,
    "field10": 1,
    "field11": 1,
    "nameEN": "Take physical damage"
  },
  {
    "id": 119,
    "nameCN": "受法术伤害",
    "category": "战斗隐藏",
    "scale": 25,
    "valueType": "百分比",
    "field5": 0,
    "calculationType": "乘法",
    "description": "",
    "maxValue": 95,
    "field9": 0,
    "field10": 1,
    "field11": 1,
    "nameEN": "Take damage from spells"
  },
  {
    "id": 120,
    "nameCN": "受所有伤害",
    "category": "战斗隐藏",
    "scale": 25,
    "valueType": "百分比",
    "field5": 0,
    "calculationType": "乘法",
    "description": "",
    "maxValue": 95,
    "field9": 0,
    "field10": 1,
    "field11": 1,
    "nameEN": "Take all damage"
  },
  {
    "id": 121,
    "nameCN": "受治疗效果",
    "category": "战斗隐藏",
    "scale": 25,
    "valueType": "百分比",
    "field5": 0,
    "calculationType": "乘法",
    "description": "",
    "maxValue": 100,
    "field9": 0,
    "field10": 1,
    "field11": 1,
    "nameEN": "Effect of treatment"
  },
  {
    "id": 122,
    "nameCN": "受护盾效果",
    "category": "战斗隐藏",
    "scale": 25,
    "valueType": "百分比",
    "field5": 0,
    "calculationType": "乘法",
    "description": "",
    "maxValue": 100,
    "field9": 0,
    "field10": 1,
    "field11": 1,
    "nameEN": "Shield effect"
  },
  {
    "id": 123,
    "nameCN": "受雷系伤害",
    "category": "战斗隐藏",
    "scale": 25,
    "valueType": "百分比",
    "field5": 0,
    "calculationType": "乘法",
    "description": "",
    "maxValue": 95,
    "field9": 0,
    "field10": 1,
    "field11": 1
  },
  {
    "id": 124,
    "nameCN": "受水系伤害",
    "category": "战斗隐藏",
    "scale": 25,
    "valueType": "百分比",
    "field5": 0,
    "calculationType": "乘法",
    "description": "",
    "maxValue": 95,
    "field9": 0,
    "field10": 1,
    "field11": 1
  },
  {
    "id": 125,
    "nameCN": "受火系伤害",
    "category": "战斗隐藏",
    "scale": 25,
    "valueType": "百分比",
    "field5": 0,
    "calculationType": "乘法",
    "description": "",
    "maxValue": 95,
    "field9": 0,
    "field10": 1,
    "field11": 1
  },
  {
    "id": 126,
    "nameCN": "受木系伤害",
    "category": "战斗隐藏",
    "scale": 25,
    "valueType": "百分比",
    "field5": 0,
    "calculationType": "乘法",
    "description": "",
    "maxValue": 95,
    "field9": 0,
    "field10": 1,
    "field11": 1
  },
  {
    "id": 127,
    "nameCN": "受土系伤害",
    "category": "战斗隐藏",
    "scale": 25,
    "valueType": "百分比",
    "field5": 0,
    "calculationType": "乘法",
    "description": "",
    "maxValue": 95,
    "field9": 0,
    "field10": 1,
    "field11": 1
  },
  {
    "id": 128,
    "nameCN": "受精神伤害",
    "category": "战斗隐藏",
    "scale": 25,
    "valueType": "百分比",
    "field5": 0,
    "calculationType": "乘法",
    "description": "",
    "maxValue": 95,
    "field9": 0,
    "field10": 1,
    "field11": 1
  },
  {
    "id": 129,
    "nameCN": "受神圣伤害",
    "category": "战斗隐藏",
    "scale": 25,
    "valueType": "百分比",
    "field5": 0,
    "calculationType": "乘法",
    "description": "",
    "maxValue": 95,
    "field9": 0,
    "field10": 1,
    "field11": 1
  },
  {
    "id": 130,
    "nameCN": "受黑暗伤害",
    "category": "战斗隐藏",
    "scale": 25,
    "valueType": "百分比",
    "field5": 0,
    "calculationType": "乘法",
    "description": "",
    "maxValue": 95,
    "field9": 0,
    "field10": 1,
    "field11": 1
  },
  {
    "id": 131,
    "nameCN": "生命增幅",
    "category": "技能被动",
    "scale": 100,
    "valueType": "百分比",
    "field5": 0,
    "calculationType": "增幅",
    "description": "",
    "maxValue": 0,
    "field9": 0,
    "field10": 1,
    "field11": 0,
    "nameEN": "HP bonus"
  },
  {
    "id": 132,
    "nameCN": "速度增幅",
    "category": "技能被动",
    "scale": 100,
    "valueType": "百分比",
    "field5": 0,
    "calculationType": "增幅",
    "description": "",
    "maxValue": 0,
    "field9": 0,
    "field10": 1,
    "field11": 0,
    "nameEN": "Speed bonus"
  },
  {
    "id": 133,
    "nameCN": "物攻增幅",
    "category": "技能被动",
    "scale": 100,
    "valueType": "百分比",
    "field5": 0,
    "calculationType": "增幅",
    "description": "",
    "maxValue": 0,
    "field9": 0,
    "field10": 1,
    "field11": 0,
    "nameEN": "ATK bonus"
  },
  {
    "id": 134,
    "nameCN": "物防增幅",
    "category": "技能被动",
    "scale": 100,
    "valueType": "百分比",
    "field5": 0,
    "calculationType": "增幅",
    "description": "",
    "maxValue": 0,
    "field9": 0,
    "field10": 1,
    "field11": 0,
    "nameEN": "DEF bonus"
  },
  {
    "id": 135,
    "nameCN": "法攻增幅",
    "category": "技能被动",
    "scale": 100,
    "valueType": "百分比",
    "field5": 0,
    "calculationType": "增幅",
    "description": "",
    "maxValue": 0,
    "field9": 0,
    "field10": 1,
    "field11": 0,
    "nameEN": "MATK bonus"
  },
  {
    "id": 136,
    "nameCN": "法防增幅",
    "category": "技能被动",
    "scale": 100,
    "valueType": "百分比",
    "field5": 0,
    "calculationType": "增幅",
    "description": "",
    "maxValue": 0,
    "field9": 0,
    "field10": 1,
    "field11": 0,
    "nameEN": "MDEF bonus"
  },
  {
    "id": 137,
    "nameCN": "驯兽工作效率",
    "category": "工作加成",
    "scale": 25,
    "valueType": "百分比",
    "field5": 0,
    "calculationType": "乘法",
    "description": "驯兽的",
    "maxValue": 0,
    "field9": 2500,
    "field10": 0,
    "field11": 0,
    "nameEN": "[size=12]Animals eff"
  },
  {
    "id": 138,
    "nameCN": "管理工作效率",
    "category": "工作加成",
    "scale": 25,
    "valueType": "百分比",
    "field5": 0,
    "calculationType": "乘法",
    "description": "管理的",
    "maxValue": 0,
    "field9": 2500,
    "field10": 0,
    "field11": 0,
    "nameEN": "[size=12]Manage eff"
  },
  {
    "id": 139,
    "nameCN": "锻造工作效率",
    "category": "工作加成",
    "scale": 25,
    "valueType": "百分比",
    "field5": 0,
    "calculationType": "乘法",
    "description": "锻造的",
    "maxValue": 0,
    "field9": 2500,
    "field10": 0,
    "field11": 0,
    "nameEN": "[size=12]Forge eff"
  },
  {
    "id": 140,
    "nameCN": "修习工作效率",
    "category": "工作加成",
    "scale": 25,
    "valueType": "百分比",
    "field5": 0,
    "calculationType": "乘法",
    "description": "修习的",
    "maxValue": 0,
    "field9": 2500,
    "field10": 0,
    "field11": 0,
    "nameEN": "[size=12]Study eff"
  },
  {
    "id": 141,
    "nameCN": "研究工作效率",
    "category": "工作加成",
    "scale": 25,
    "valueType": "百分比",
    "field5": 0,
    "calculationType": "乘法",
    "description": "研究的",
    "maxValue": 0,
    "field9": 2500,
    "field10": 0,
    "field11": 0,
    "nameEN": "[size=12]Research eff"
  },
  {
    "id": 142,
    "nameCN": "建造工作效率",
    "category": "工作加成",
    "scale": 25,
    "valueType": "百分比",
    "field5": 0,
    "calculationType": "乘法",
    "description": "建造的",
    "maxValue": 0,
    "field9": 2500,
    "field10": 0,
    "field11": 0,
    "nameEN": "[size=12]Build eff"
  },
  {
    "id": 143,
    "nameCN": "商业工作效率",
    "category": "工作加成",
    "scale": 25,
    "valueType": "百分比",
    "field5": 0,
    "calculationType": "乘法",
    "description": "商业的",
    "maxValue": 0,
    "field9": 2500,
    "field10": 0,
    "field11": 0,
    "nameEN": "[size=10]Commerce eff"
  },
  {
    "id": 144,
    "nameCN": "合成工作效率",
    "category": "工作加成",
    "scale": 25,
    "valueType": "百分比",
    "field5": 0,
    "calculationType": "乘法",
    "description": "合成的",
    "maxValue": 0,
    "field9": 2500,
    "field10": 0,
    "field11": 0,
    "nameEN": "[size=12]Pharmacy eff"
  },
  {
    "id": 145,
    "nameCN": "计略工作效率",
    "category": "工作加成",
    "scale": 25,
    "valueType": "百分比",
    "field5": 0,
    "calculationType": "乘法",
    "description": "战略的",
    "maxValue": 0,
    "field9": 2500,
    "field10": 0,
    "field11": 0,
    "nameEN": "[size=12]Strategy eff"
  },
  {
    "id": 146,
    "nameCN": "收藏工作效率",
    "category": "工作加成",
    "scale": 25,
    "valueType": "百分比",
    "field5": 0,
    "calculationType": "乘法",
    "description": "收藏的",
    "maxValue": 0,
    "field9": 2500,
    "field10": 0,
    "field11": 0,
    "nameEN": "[size=12]History eff"
  },
  {
    "id": 147,
    "nameCN": "勇额外成长",
    "category": "额外成长",
    "scale": 10,
    "valueType": "小数",
    "field5": 0,
    "calculationType": "乘法",
    "description": "勇敢的",
    "maxValue": 0,
    "field9": 0,
    "field10": 1,
    "field11": 0
  },
  {
    "id": 148,
    "nameCN": "智额外成长",
    "category": "额外成长",
    "scale": 10,
    "valueType": "小数",
    "field5": 0,
    "calculationType": "乘法",
    "description": "智慧的",
    "maxValue": 0,
    "field9": 0,
    "field10": 1,
    "field11": 0
  },
  {
    "id": 149,
    "nameCN": "体额外成长",
    "category": "额外成长",
    "scale": 10,
    "valueType": "小数",
    "field5": 0,
    "calculationType": "乘法",
    "description": "体能的",
    "maxValue": 0,
    "field9": 0,
    "field10": 1,
    "field11": 0
  },
  {
    "id": 150,
    "nameCN": "敏额外成长",
    "category": "额外成长",
    "scale": 10,
    "valueType": "小数",
    "field5": 0,
    "calculationType": "乘法",
    "description": "敏捷的",
    "maxValue": 0,
    "field9": 0,
    "field10": 1,
    "field11": 0
  },
  {
    "id": 151,
    "nameCN": "精额外成长",
    "category": "额外成长",
    "scale": 10,
    "valueType": "小数",
    "field5": 0,
    "calculationType": "乘法",
    "description": "精神的",
    "maxValue": 0,
    "field9": 0,
    "field10": 1,
    "field11": 0
  },
  {
    "id": 152,
    "nameCN": "货币掉落",
    "category": "独立",
    "scale": 5,
    "valueType": "百分比",
    "field5": 0,
    "calculationType": "乘法",
    "description": "财富的",
    "maxValue": 0,
    "field9": 0,
    "field10": 1,
    "field11": 0,
    "nameEN": "[size=10]Currency drop"
  },
  {
    "id": 153,
    "nameCN": "<汉末武技>威力",
    "category": "技能组",
    "scale": 20,
    "valueType": "百分比",
    "field5": 0,
    "calculationType": "乘法",
    "description": "无",
    "maxValue": 0,
    "field9": 1500,
    "field10": 1,
    "field11": 0,
    "nameEN": "[size=8]< Han > bonus"
  },
  {
    "id": 154,
    "nameCN": "<曹魏虎卫>威力",
    "category": "技能组",
    "scale": 20,
    "valueType": "百分比",
    "field5": 0,
    "calculationType": "乘法",
    "description": "无",
    "maxValue": 0,
    "field9": 1500,
    "field10": 1,
    "field11": 0,
    "nameEN": "[size=8]< Cao Wei > bonus"
  },
  {
    "id": 155,
    "nameCN": "<蜀汉青书>威力",
    "category": "技能组",
    "scale": 20,
    "valueType": "百分比",
    "field5": 0,
    "calculationType": "乘法",
    "description": "无",
    "maxValue": 0,
    "field9": 1500,
    "field10": 1,
    "field11": 0,
    "nameEN": "[size=8]< Shu Han > bonus"
  },
  {
    "id": 156,
    "nameCN": "<东吴射术>威力",
    "category": "技能组",
    "scale": 20,
    "valueType": "百分比",
    "field5": 0,
    "calculationType": "乘法",
    "description": "无",
    "maxValue": 0,
    "field9": 1500,
    "field10": 1,
    "field11": 0,
    "nameEN": "[size=8]< Dong Wu > bonus"
  },
  {
    "id": 157,
    "nameCN": "<丐帮技能>威力",
    "category": "技能组",
    "scale": 20,
    "valueType": "百分比",
    "field5": 0,
    "calculationType": "乘法",
    "description": "无",
    "maxValue": 0,
    "field9": 1500,
    "field10": 1,
    "field11": 0,
    "nameEN": "[size=8]< Beggars > bonus"
  },
  {
    "id": 158,
    "nameCN": "<少林技能>威力",
    "category": "技能组",
    "scale": 20,
    "valueType": "百分比",
    "field5": 0,
    "calculationType": "乘法",
    "description": "无",
    "maxValue": 0,
    "field9": 1500,
    "field10": 1,
    "field11": 0,
    "nameEN": "[size=8]< Shaolin > bonus"
  },
  {
    "id": 159,
    "nameCN": "<华山技能>威力",
    "category": "技能组",
    "scale": 20,
    "valueType": "百分比",
    "field5": 0,
    "calculationType": "乘法",
    "description": "无",
    "maxValue": 0,
    "field9": 1500,
    "field10": 1,
    "field11": 0,
    "nameEN": "[size=8]< Huashan > bonus"
  },
  {
    "id": 160,
    "nameCN": "<武当技能>威力",
    "category": "技能组",
    "scale": 20,
    "valueType": "百分比",
    "field5": 0,
    "calculationType": "乘法",
    "description": "无",
    "maxValue": 0,
    "field9": 1500,
    "field10": 1,
    "field11": 0,
    "nameEN": "[size=8]< Wudang > bonus"
  },
  {
    "id": 161,
    "nameCN": "<摸金技能>威力",
    "category": "技能组",
    "scale": 20,
    "valueType": "百分比",
    "field5": 0,
    "calculationType": "乘法",
    "description": "无",
    "maxValue": 0,
    "field9": 1500,
    "field10": 1,
    "field11": 0,
    "nameEN": "[size=8]< Mojin > bonus"
  },
  {
    "id": 162,
    "nameCN": "<搬山技能>威力",
    "category": "技能组",
    "scale": 20,
    "valueType": "百分比",
    "field5": 0,
    "calculationType": "乘法",
    "description": "无",
    "maxValue": 0,
    "field9": 1500,
    "field10": 1,
    "field11": 0,
    "nameEN": "[size=8]< Banshan > bonus"
  },
  {
    "id": 163,
    "nameCN": "<卸岭技能>威力",
    "category": "技能组",
    "scale": 20,
    "valueType": "百分比",
    "field5": 0,
    "calculationType": "乘法",
    "description": "无",
    "maxValue": 0,
    "field9": 1500,
    "field10": 1,
    "field11": 0,
    "nameEN": "[size=8]< Xieling > bonus"
  },
  {
    "id": 164,
    "nameCN": "<发丘技能>威力",
    "category": "技能组",
    "scale": 20,
    "valueType": "百分比",
    "field5": 0,
    "calculationType": "乘法",
    "description": "无",
    "maxValue": 0,
    "field9": 1500,
    "field10": 1,
    "field11": 0,
    "nameEN": "[size=8]< Faqiu > bonus"
  },
  {
    "id": 165,
    "nameCN": "<耶路技能>威力",
    "category": "技能组",
    "scale": 20,
    "valueType": "百分比",
    "field5": 0,
    "calculationType": "乘法",
    "description": "无",
    "maxValue": 0,
    "field9": 1500,
    "field10": 1,
    "field11": 0,
    "nameEN": "[size=8]< Jerusalem > bonus"
  },
  {
    "id": 166,
    "nameCN": "<十字技能>威力",
    "category": "技能组",
    "scale": 20,
    "valueType": "百分比",
    "field5": 0,
    "calculationType": "乘法",
    "description": "无",
    "maxValue": 0,
    "field9": 1500,
    "field10": 1,
    "field11": 0,
    "nameEN": "[size=8]< Crusaders > bonus"
  },
  {
    "id": 167,
    "nameCN": "<阿拉技能>威力",
    "category": "技能组",
    "scale": 20,
    "valueType": "百分比",
    "field5": 0,
    "calculationType": "乘法",
    "description": "无",
    "maxValue": 0,
    "field9": 1500,
    "field10": 1,
    "field11": 0,
    "nameEN": "[size=8]< Arab > bonus"
  },
  {
    "id": 168,
    "nameCN": "<人间技能>威力",
    "category": "技能组",
    "scale": 20,
    "valueType": "百分比",
    "field5": 0,
    "calculationType": "乘法",
    "description": "无",
    "maxValue": 0,
    "field9": 1500,
    "field10": 1,
    "field11": 0,
    "nameEN": "[size=8]< temple > bonus"
  },
  {
    "id": 169,
    "nameCN": "<饿鬼技能>威力",
    "category": "技能组",
    "scale": 20,
    "valueType": "百分比",
    "field5": 0,
    "calculationType": "乘法",
    "description": "无",
    "maxValue": 0,
    "field9": 1500,
    "field10": 1,
    "field11": 0,
    "nameEN": "[size=8]< Ghost > bonus"
  },
  {
    "id": 170,
    "nameCN": "<妖灵技能>威力",
    "category": "技能组",
    "scale": 20,
    "valueType": "百分比",
    "field5": 0,
    "calculationType": "乘法",
    "description": "无",
    "maxValue": 0,
    "field9": 1500,
    "field10": 1,
    "field11": 0,
    "nameEN": "[size=8]< Spirit > bonus"
  },
  {
    "id": 171,
    "nameCN": "<幕府技能>威力",
    "category": "技能组",
    "scale": 20,
    "valueType": "百分比",
    "field5": 0,
    "calculationType": "乘法",
    "description": "无",
    "maxValue": 0,
    "field9": 1500,
    "field10": 1,
    "field11": 0,
    "nameEN": "[size=8]< Shogunate > bonus"
  },
  {
    "id": 172,
    "nameCN": "<织田技能>威力",
    "category": "技能组",
    "scale": 20,
    "valueType": "百分比",
    "field5": 0,
    "calculationType": "乘法",
    "description": "无",
    "maxValue": 0,
    "field9": 1500,
    "field10": 1,
    "field11": 0,
    "nameEN": "[size=8]< Oda > bonus"
  },
  {
    "id": 173,
    "nameCN": "<德川技能>威力",
    "category": "技能组",
    "scale": 20,
    "valueType": "百分比",
    "field5": 0,
    "calculationType": "乘法",
    "description": "无",
    "maxValue": 0,
    "field9": 1500,
    "field10": 1,
    "field11": 0,
    "nameEN": "[size=8]< Tokugawa > bonus"
  },
  {
    "id": 174,
    "nameCN": "<英美技能>威力",
    "category": "技能组",
    "scale": 20,
    "valueType": "百分比",
    "field5": 0,
    "calculationType": "乘法",
    "description": "无",
    "maxValue": 0,
    "field9": 1500,
    "field10": 1,
    "field11": 0,
    "nameEN": "[size=8]< Allied > bonus"
  },
  {
    "id": 175,
    "nameCN": "<苏联技能>威力",
    "category": "技能组",
    "scale": 20,
    "valueType": "百分比",
    "field5": 0,
    "calculationType": "乘法",
    "description": "无",
    "maxValue": 0,
    "field9": 1500,
    "field10": 1,
    "field11": 0,
    "nameEN": "[size=8]< Soviet > bonus"
  },
  {
    "id": 176,
    "nameCN": "<德国技能>威力",
    "category": "技能组",
    "scale": 20,
    "valueType": "百分比",
    "field5": 0,
    "calculationType": "乘法",
    "description": "无",
    "maxValue": 0,
    "field9": 1500,
    "field10": 1,
    "field11": 0,
    "nameEN": "[size=8]< Germany > bonus"
  },
  {
    "id": 177,
    "nameCN": "<仙域技能>威力",
    "category": "技能组",
    "scale": 20,
    "valueType": "百分比",
    "field5": 0,
    "calculationType": "乘法",
    "description": "无",
    "maxValue": 0,
    "field9": 1500,
    "field10": 1,
    "field11": 0,
    "nameEN": "[size=8]< Xianzong > bonus"
  },
  {
    "id": 178,
    "nameCN": "<玄天技能>威力",
    "category": "技能组",
    "scale": 20,
    "valueType": "百分比",
    "field5": 0,
    "calculationType": "乘法",
    "description": "无",
    "maxValue": 0,
    "field9": 1500,
    "field10": 1,
    "field11": 0,
    "nameEN": "[size=8]< Xuantian > bonus"
  },
  {
    "id": 179,
    "nameCN": "<合欢技能>威力",
    "category": "技能组",
    "scale": 20,
    "valueType": "百分比",
    "field5": 0,
    "calculationType": "乘法",
    "description": "无",
    "maxValue": 0,
    "field9": 1500,
    "field10": 1,
    "field11": 0,
    "nameEN": "[size=8]< Hehuan > bonus"
  },
  {
    "id": 180,
    "nameCN": "<地球技能>威力",
    "category": "技能组",
    "scale": 20,
    "valueType": "百分比",
    "field5": 0,
    "calculationType": "乘法",
    "description": "无",
    "maxValue": 0,
    "field9": 1500,
    "field10": 1,
    "field11": 0,
    "nameEN": "[size=8]< Earth > bonus"
  },
  {
    "id": 181,
    "nameCN": "<宇宙技能>威力",
    "category": "技能组",
    "scale": 20,
    "valueType": "百分比",
    "field5": 0,
    "calculationType": "乘法",
    "description": "无",
    "maxValue": 0,
    "field9": 1500,
    "field10": 1,
    "field11": 0,
    "nameEN": "[size=8]< Viss > bonus"
  },
  {
    "id": 182,
    "nameCN": "<维斯技能>威力",
    "category": "技能组",
    "scale": 20,
    "valueType": "百分比",
    "field5": 0,
    "calculationType": "乘法",
    "description": "无",
    "maxValue": 0,
    "field9": 1500,
    "field10": 1,
    "field11": 0,
    "nameEN": "[size=8]< Duchy > bonus"
  },
  {
    "id": 183,
    "nameCN": "<落云技能>威力",
    "category": "技能组",
    "scale": 20,
    "valueType": "百分比",
    "field5": 0,
    "calculationType": "乘法",
    "description": "无",
    "maxValue": 0,
    "field9": 1500,
    "field10": 1,
    "field11": 0,
    "nameEN": "[size=8]< Luoyun > bonus"
  },
  {
    "id": 184,
    "nameCN": "<卡玛技能>威力",
    "category": "技能组",
    "scale": 20,
    "valueType": "百分比",
    "field5": 0,
    "calculationType": "乘法",
    "description": "无",
    "maxValue": 0,
    "field9": 1500,
    "field10": 1,
    "field11": 0,
    "nameEN": "[size=8]< Karma > bonus"
  },
  {
    "id": 185,
    "nameCN": "<慕然技能>威力",
    "category": "技能组",
    "scale": 20,
    "valueType": "百分比",
    "field5": 0,
    "calculationType": "乘法",
    "description": "无",
    "maxValue": 0,
    "field9": 1500,
    "field10": 1,
    "field11": 0,
    "nameEN": "[size=8]< Muran > bonus"
  },
  {
    "id": 186,
    "nameCN": "<中立技能>威力",
    "category": "技能组",
    "scale": 20,
    "valueType": "百分比",
    "field5": 0,
    "calculationType": "乘法",
    "description": "无",
    "maxValue": 0,
    "field9": 1500,
    "field10": 1,
    "field11": 0,
    "nameEN": "[size=8]< Unaligned > bonus"
  },
  {
    "id": 187,
    "nameCN": "<联盟技能>威力",
    "category": "技能组",
    "scale": 20,
    "valueType": "百分比",
    "field5": 0,
    "calculationType": "乘法",
    "description": "无",
    "maxValue": 0,
    "field9": 1500,
    "field10": 1,
    "field11": 0,
    "nameEN": "[size=8]< Warband > bonus"
  },
  {
    "id": 188,
    "nameCN": "<部落技能>威力",
    "category": "技能组",
    "scale": 20,
    "valueType": "百分比",
    "field5": 0,
    "calculationType": "乘法",
    "description": "无",
    "maxValue": 0,
    "field9": 1500,
    "field10": 1,
    "field11": 0,
    "nameEN": "[size=8]< Concord > bonus"
  },
  {
    "id": 189,
    "nameCN": "<至尊技能>威力",
    "category": "技能组",
    "scale": 20,
    "valueType": "百分比",
    "field5": 0,
    "calculationType": "乘法",
    "description": "无",
    "maxValue": 0,
    "field9": 1500,
    "field10": 1,
    "field11": 0,
    "nameEN": "[size=8]< Archmage > bonus"
  },
  {
    "id": 190,
    "nameCN": "<暗裔技能>威力",
    "category": "技能组",
    "scale": 20,
    "valueType": "百分比",
    "field5": 0,
    "calculationType": "乘法",
    "description": "无",
    "maxValue": 0,
    "field9": 1500,
    "field10": 1,
    "field11": 0,
    "nameEN": "[size=8]< Dark > bonus"
  },
  {
    "id": 191,
    "nameCN": "<变种技能>威力",
    "category": "技能组",
    "scale": 20,
    "valueType": "百分比",
    "field5": 0,
    "calculationType": "乘法",
    "description": "无",
    "maxValue": 0,
    "field9": 1500,
    "field10": 1,
    "field11": 0,
    "nameEN": "[size=8]< Mutant > bonus"
  },
  {
    "id": 192,
    "nameCN": "<大唐技能>威力",
    "category": "技能组",
    "scale": 20,
    "valueType": "百分比",
    "field5": 0,
    "calculationType": "乘法",
    "description": "无",
    "maxValue": 0,
    "field9": 1500,
    "field10": 1,
    "field11": 0,
    "nameEN": "[size=8]< Tang > bonus"
  },
  {
    "id": 193,
    "nameCN": "<妖族技能>威力",
    "category": "技能组",
    "scale": 20,
    "valueType": "百分比",
    "field5": 0,
    "calculationType": "乘法",
    "description": "无",
    "maxValue": 0,
    "field9": 1500,
    "field10": 1,
    "field11": 0,
    "nameEN": "[size=8]< Demon > bonus"
  },
  {
    "id": 194,
    "nameCN": "<天庭技能>威力",
    "category": "技能组",
    "scale": 20,
    "valueType": "百分比",
    "field5": 0,
    "calculationType": "乘法",
    "description": "无",
    "maxValue": 0,
    "field9": 1500,
    "field10": 1,
    "field11": 0,
    "nameEN": "[size=8]< Buddhism > bonus"
  },
  {
    "id": 195,
    "nameCN": "<雷系技能>威力",
    "category": "元素类",
    "scale": 20,
    "valueType": "百分比",
    "field5": 0,
    "calculationType": "乘法",
    "description": "无",
    "maxValue": 0,
    "field9": 1000,
    "field10": 1,
    "field11": 0,
    "nameEN": "[size=8]<Lightning Skill>bonus"
  },
  {
    "id": 196,
    "nameCN": "<水系技能>威力",
    "category": "元素类",
    "scale": 20,
    "valueType": "百分比",
    "field5": 0,
    "calculationType": "乘法",
    "description": "无",
    "maxValue": 0,
    "field9": 1000,
    "field10": 1,
    "field11": 0,
    "nameEN": "[size=8]<Water Skill>bonus"
  },
  {
    "id": 197,
    "nameCN": "<火系技能>威力",
    "category": "元素类",
    "scale": 20,
    "valueType": "百分比",
    "field5": 0,
    "calculationType": "乘法",
    "description": "无",
    "maxValue": 0,
    "field9": 1000,
    "field10": 1,
    "field11": 0,
    "nameEN": "[size=8]<Fire Skill>bonus"
  },
  {
    "id": 198,
    "nameCN": "<木系技能>威力",
    "category": "元素类",
    "scale": 20,
    "valueType": "百分比",
    "field5": 0,
    "calculationType": "乘法",
    "description": "无",
    "maxValue": 0,
    "field9": 1000,
    "field10": 1,
    "field11": 0,
    "nameEN": "[size=8]<Wood Skill> bonus"
  },
  {
    "id": 199,
    "nameCN": "<土系技能>威力",
    "category": "元素类",
    "scale": 20,
    "valueType": "百分比",
    "field5": 0,
    "calculationType": "乘法",
    "description": "无",
    "maxValue": 0,
    "field9": 1000,
    "field10": 1,
    "field11": 0,
    "nameEN": "[size=8]<Earth Skill> bonus"
  },
  {
    "id": 200,
    "nameCN": "<精神技能>威力",
    "category": "元素类",
    "scale": 20,
    "valueType": "百分比",
    "field5": 0,
    "calculationType": "乘法",
    "description": "无",
    "maxValue": 0,
    "field9": 1000,
    "field10": 1,
    "field11": 0,
    "nameEN": "[size=8]<Spirit Skill> bonus"
  },
  {
    "id": 201,
    "nameCN": "<神圣技能>威力",
    "category": "元素类",
    "scale": 20,
    "valueType": "百分比",
    "field5": 0,
    "calculationType": "乘法",
    "description": "无",
    "maxValue": 0,
    "field9": 1000,
    "field10": 1,
    "field11": 0,
    "nameEN": "[size=8]<Holy Skill>bonus"
  },
  {
    "id": 202,
    "nameCN": "<黑暗技能>威力",
    "category": "元素类",
    "scale": 20,
    "valueType": "百分比",
    "field5": 0,
    "calculationType": "乘法",
    "description": "无",
    "maxValue": 0,
    "field9": 1000,
    "field10": 1,
    "field11": 0,
    "nameEN": "[size=8]<Dark Skill> bonus"
  }
]